sudogpt/__init__.py
sudogpt/command_line.py
sudogpt/prompts.py
sudogpt-0.3.dist-info/METADATA
sudogpt-0.3.dist-info/WHEEL
sudogpt-0.3.dist-info/entry_points.txt
sudogpt-0.3.dist-info/top_level.txt
sudogpt-0.3.dist-info/RECORD
