Metadata-Version: 2.1
Name: sudogpt
Version: 0.3
Summary: Let openai into your computer
Home-page: https://github.com/tim-sparq/sudogpt
Author: Tim Savage
Author-email: tim.savage@datsparq.ai
License: MIT
Requires-Dist: openai
